ovsdbmanager/__init__.py
ovsdbmanager/_version.py
ovsdbmanager/condition.py
ovsdbmanager/exception.py
ovsdbmanager/method.py
ovsdbmanager/operation.py
ovsdbmanager/query.py
ovsdbmanager/utils.py
ovsdbmanager/db/__init__.py
ovsdbmanager/db/bridge.py
ovsdbmanager/db/controller.py
ovsdbmanager/db/interface.py
ovsdbmanager/db/ovs.py
ovsdbmanager/db/port.py
ovsdbmanager/tables/__init__.py
ovsdbmanager/tables/bridge.py
ovsdbmanager/tables/controller.py
ovsdbmanager/tables/interface.py
ovsdbmanager/tables/ovs.py
ovsdbmanager/tables/port.py
tests/__init__.py
tests/test_ovsdbmanager.py
ovsdbmanager-0.1.6.dist-info/COPYING
ovsdbmanager-0.1.6.dist-info/METADATA
ovsdbmanager-0.1.6.dist-info/WHEEL
ovsdbmanager-0.1.6.dist-info/top_level.txt
ovsdbmanager-0.1.6.dist-info/RECORD
