Metadata-Version: 2.1
Name: ovsdbmanager
Version: 0.1.6
Summary: A Python3 OVSDB API
Home-page: https://github.com/Fundacio-i2CAT/ovsdb-manager
Author: Ferran Cañellas
Author-email: ferran.canellas@i2cat.net
License: UNKNOWN
Platform: UNKNOWN
Classifier: Programming Language :: Python :: 3
Classifier: License :: OSI Approved :: GNU Affero General Public License v3 or later (AGPLv3+)
Classifier: Development Status :: 4 - Beta
Classifier: Intended Audience :: Developers
Classifier: Operating System :: POSIX :: Linux
Requires-Python: >=3.5
